muller/__init__.py
muller/__main__.py
muller/commandline_parser.py
muller/muller_workflow.py
muller/treetools.py
muller/widgets.py
muller/clustering/__init__.py
muller/clustering/filters.py
muller/clustering/generate_genotypes.py
muller/clustering/methods/__init__.py
muller/clustering/methods/hierarchical_method.py
muller/clustering/methods/population_genotypes.py
muller/clustering/methods/twostep_main.py
muller/clustering/methods/twostep_unlink.py
muller/clustering/metrics/__init__.py
muller/clustering/metrics/distance_cache.py
muller/clustering/metrics/distance_calculator.py
muller/clustering/metrics/distance_methods.py
muller/dataio/__init__.py
muller/dataio/filenames.py
muller/dataio/generate_output.py
muller/dataio/generate_scripts.py
muller/dataio/generate_tables.py
muller/dataio/genotypecollection.py
muller/dataio/import_file.py
muller/dataio/import_tables.py
muller/dataio/import_trajectories.py
muller/dataio/mullerformat.py
muller/graphics/__init__.py
muller/graphics/dendrogram.py
muller/graphics/flowchart.py
muller/graphics/heatmap.py
muller/graphics/muller_plot.py
muller/graphics/timeseries_plots.py
muller/graphics/palettes/__init__.py
muller/graphics/palettes/colorset.py
muller/graphics/palettes/general.py
muller/graphics/palettes/palette_annotation.py
muller/graphics/palettes/palette_distinctive.py
muller/graphics/palettes/palette_lineage.py
muller/inheritance/__init__.py
muller/inheritance/areascore.py
muller/inheritance/genotype_ancestry.py
muller/inheritance/genotype_lineage.py
muller/inheritance/genotype_reorder.py
muller/inheritance/scoring.py
muller/inheritance/timepoint_detection.py
muller-0.6.0.data/scripts/lineage
muller-0.6.0.dist-info/LICENSE
muller-0.6.0.dist-info/METADATA
muller-0.6.0.dist-info/WHEEL
muller-0.6.0.dist-info/top_level.txt
muller-0.6.0.dist-info/RECORD
