Metadata-Version: 2.1
Name: muller
Version: 0.6.0
Summary: A set of scripts to cluster mutational trajectories into genotypes and cluster genotypes by background
Home-page: https://github.com/cdeitrick/muller_diagrams
Author: chris deitrick
Author-email: chrisdeitrick1@gmail.com
License: MIT
Platform: UNKNOWN
Classifier: Programming Language :: Python :: 3
Classifier: License :: OSI Approved :: MIT License
Classifier: Operating System :: OS Independent
Provides: m
Provides: u
Provides: l
Provides: l
Provides: e
Provides: r
Requires-Dist: pandas
Requires-Dist: loguru
Requires-Dist: scipy
Requires-Dist: matplotlib
Requires-Dist: graphviz
Requires-Dist: pygraphviz
Requires-Dist: seaborn
Requires-Dist: numpy
Requires-Dist: xlrd
Provides-Extra: additional_support_for_parsing_files
Requires-Dist: beautifulsoup4 ; extra == 'additional_support_for_parsing_files'
Provides-Extra: list_similar_annotations_when_selecting_genotypes
Requires-Dist: fuzzywuzzy ; extra == 'list_similar_annotations_when_selecting_genotypes'
Provides-Extra: show_progressbar_for_large_datasets
Requires-Dist: tqdm ; extra == 'show_progressbar_for_large_datasets'
Provides-Extra: to_run_tests
Requires-Dist: pytest ; extra == 'to_run_tests'
